[
  {
    "name": "vue",
    "version": "3.2.37"
  },
  {
    "name": "angular",
    "version": "14.1.2"
  },
  {
    "name": "react",
    "version": "18.2.0"
  },
  {
    "name": "ember",
    "version": "4.6.0"
  },
  {
    "name": "svelte",
    "version": "3.49.0"
  },
  {
    "name": "aurelia",
    "version": "1.4.1"
  },
  {
    "name": "next",
    "version": "12.2.5"
  },
  {
    "name": "elm",
    "version": "0.19.1-5"
  },
  {
    "name": "typescript",
    "version": "4.7.4"
  },
  {
    "name": "flow",
    "version": "0.184.0"
  },
  {
    "name": "rxjs",
    "version": "7.5.6"
  }
]