[
  {
    "name": "vue",
    "total": 93962,
    "featured": 2,
    "noAnswers": 18762
  },
  {
    "name": "angular",
    "total": 278463,
    "featured": 5,
    "noAnswers": 52777
  },
  {
    "name": "react",
    "total": 392270,
    "featured": 26,
    "noAnswers": 81819
  },
  {
    "name": "ember",
    "total": 23868,
    "featured": 0,
    "noAnswers": 2641
  },
  {
    "name": "svelte",
    "total": 3180,
    "featured": 0,
    "noAnswers": 588
  },
  {
    "name": "aurelia",
    "total": 3401,
    "featured": 0,
    "noAnswers": 482
  },
  {
    "name": "elm",
    "total": 1833,
    "featured": 0,
    "noAnswers": 102
  }
]